pyttsreverso/__init__.py
pyttsreverso/pyttsreverso.py
pyttsreverso-0.4.dist-info/METADATA
pyttsreverso-0.4.dist-info/WHEEL
pyttsreverso-0.4.dist-info/top_level.txt
pyttsreverso-0.4.dist-info/RECORD
