Metadata-Version: 2.1
Name: pyttsreverso
Version: 0.4
Summary: Useful tools to work with Resrervo TTS in Python
Home-page: https://github.com/rt400/pyttsreverso
Author: Yuval Mejahez
Author-email: yuval.teltech@gmail.com
License: MIT
Download-URL: https://pypi.org/project/pyttsreverso/
Keywords: Resrervo,TTS,ResrervoTTS
Platform: UNKNOWN
